CognitiveModulePlatform/__init__.py
CognitiveModulePlatform/create_data_medifit.py
CognitiveModulePlatform/data_creation.py
CognitiveModulePlatform-0.1.dist-info/METADATA
CognitiveModulePlatform-0.1.dist-info/WHEEL
CognitiveModulePlatform-0.1.dist-info/top_level.txt
CognitiveModulePlatform-0.1.dist-info/RECORD
