Metadata-Version: 2.1
Name: CognitiveModulePlatform
Version: 0.1
Summary: A description of your library
Home-page: UNKNOWN
Author: Your Name
Author-email: your.email@example.com
License: UNKNOWN
Platform: UNKNOWN
